pynav/__init__.py
pynav/browser.py
pynav/response.py
pynav/useragent.py
pynav-1.0.dist-info/COPYING.LESSER
pynav-1.0.dist-info/METADATA
pynav-1.0.dist-info/WHEEL
pynav-1.0.dist-info/top_level.txt
pynav-1.0.dist-info/RECORD
