Metadata-Version: 1.2
Name: pynav
Version: 1.0
Summary: Python programmatic web browser to fetch data and test web sites
Home-page: http://bitbucket.org/sloft/pynav/
Author: sloft
Author-email: nomail@example.com
License: GNU Lesser General Public License (LGPL)
Download-URL: http://bitbucket.org/sloft/pynav/downloads/
Keywords: programmatic,web,browser
Platform: UNKNOWN
Classifier: Programming Language :: Python
Classifier: Programming Language :: Python :: 3.5
Classifier: Programming Language :: Python :: 3.6
Classifier: Programming Language :: Python :: 3.7
Classifier: Operating System :: OS Independent
Classifier: License :: OSI Approved :: GNU Library or Lesser General Public License (LGPL)
Classifier: Development Status :: 4 - Beta
Classifier: Environment :: Console
Classifier: Topic :: Internet
Classifier: Intended Audience :: Developers
Classifier: Topic :: Internet :: WWW/HTTP
Classifier: Topic :: Internet :: WWW/HTTP :: Browsers
Classifier: Topic :: Internet :: WWW/HTTP :: Indexing/Search
Classifier: Topic :: Internet :: WWW/HTTP :: Site Management
Classifier: Topic :: Internet :: WWW/HTTP :: Site Management :: Link Checking
Classifier: Topic :: Software Development :: Libraries
Classifier: Topic :: Software Development :: Libraries :: Python Modules
Requires-Python: >=3.5
